toml_tools/__init__.py
toml_tools/_helpers.py
toml_tools/_parser.py
toml_tools/_re.py
toml_tools/_writer.py
toml_tools-1.0.0.dist-info/LICENSE
toml_tools-1.0.0.dist-info/LICENSE-HEADER
toml_tools-1.0.0.dist-info/WHEEL
toml_tools-1.0.0.dist-info/METADATA
toml_tools-1.0.0.dist-info/RECORD
