Metadata-Version: 2.1
Name: toml_tools
Version: 1.0.0
Summary: Tomli and Tomli-W for Python 2 and Iron Python
Keywords: toml
Author-email: Taneli Hukkinen <hukkin@users.noreply.github.com>, James Parrott <james.parrott@proton.me>
Requires-Python: >=2.7
Classifier: License :: OSI Approved :: MIT License
Classifier: Operating System :: MacOS
Classifier: Operating System :: Microsoft :: Windows
Classifier: Operating System :: POSIX :: Linux
Classifier: Programming Language :: Python :: 3 :: Only
Classifier: Programming Language :: Python :: Implementation :: CPython
Classifier: Topic :: Software Development :: Libraries :: Python Modules
Classifier: Typing :: Typed
Project-URL: Homepage, https://github.com/JamesParrott/toml_tools
